niftiai/__init__.py
niftiai/augment.py
niftiai/core.py
niftiai/data.py
niftiai/learner.py
niftiai/models/__init__.py
niftiai/models/resnet3d.py
niftiai/models/tinycnn3d.py
niftiai/transforms.py
niftiai-0.3.0.dist-info/METADATA
niftiai-0.3.0.dist-info/WHEEL
niftiai-0.3.0.dist-info/licenses/LICENSE
niftiai-0.3.0.dist-info/RECORD
