Metadata-Version: 2.4
Name: niftiai
Version: 0.3.0
Summary: Train neural nets on 3D images (e.g. MRIs) 🧠
License: MIT
License-File: LICENSE
Author: codingfisch
Author-email: l_fisc17@wwu.de
Requires-Python: >=3.9,<4.0
Classifier: Intended Audience :: Science/Research
Classifier: License :: OSI Approved :: MIT License
Classifier: Operating System :: OS Independent
Classifier: Programming Language :: Python :: 3
Classifier: Programming Language :: Python :: 3.9
Classifier: Programming Language :: Python :: 3.10
Classifier: Programming Language :: Python :: 3.11
Classifier: Programming Language :: Python :: 3.12
Classifier: Programming Language :: Python :: 3.13
Classifier: Programming Language :: Python :: 3.14
Requires-Dist: fastai (>=2.8.1)
Requires-Dist: mriaug
Requires-Dist: niftiview
Requires-Dist: resize-right
Requires-Dist: unet3d
Project-URL: Repository, https://github.com/codingfisch/niftiai
